pantilt/__init__.py
pantilt/cam_pantilt.py
pantilt/joystick.py
pantilt/pantilt.py
pantilt/servo_test.py
utils/__init__.py
pantilt-0.0.2.dist-info/LICENSE
pantilt-0.0.2.dist-info/METADATA
pantilt-0.0.2.dist-info/WHEEL
pantilt-0.0.2.dist-info/top_level.txt
pantilt-0.0.2.dist-info/RECORD
