Metadata-Version: 2.1
Name: pantilt
Version: 0.0.2
Summary: A pantilt control utility
Home-page: https://github.com/youyoubilly/pantilt
Author: Billy Wang, Kevin Peng, Shawn Ling
License: UNKNOWN
Keywords: pan tilt,servo control
Platform: UNKNOWN
Classifier: Programming Language :: Python :: 3
Classifier: License :: OSI Approved :: MIT License
Classifier: Operating System :: OS Independent
Requires-Python: >=3.6
Requires-Dist: bcam
Requires-Dist: Adafruit-PCA9685
